LICENSE
MANIFEST.in
README.md
setup.py
abyss/__init__.py
abyss/account.py
abyss/client.py
abyss/db.py
abyss/entity.py
abyss/gamestate.py
abyss/mapstate.py
abyss.egg-info/PKG-INFO
abyss.egg-info/SOURCES.txt
abyss.egg-info/dependency_links.txt
abyss.egg-info/entry_points.txt
abyss.egg-info/requires.txt
abyss.egg-info/top_level.txt
abyss/server/__init__.py
abyss/server/app.py